<?xml version='1.0' encoding='UTF-8'?>
<!--
* === All parameters need to be INTEGER ===
*
* - Main node within <Inputs> and </Inputs>
*
* - Fixed-input parameters are with syntax:
*
*    <Input>
*      <Name>parameter_name</Name>
*      <Value>0.5</Value>
*    </Input>
*
* - Optimizable parameter are with syntax:
*
*    <OptRange>
*      <Name>parameter_name</Name>
*      <Start>1</Start>
*      <Stop>20</Stop>
*      <Step>1</Step>
*    </OptRange>
*
* For Backtest: only the <Start> value of <OptRange> parameters is read.
-->
<Inputs>
    <Input>
        <Name>epsilon</Name>            <!-- always 0 (used in stability test) -->
        <Value>0</Value>
    </Input>
</Inputs>
